{"brand":"Yakima","sku":"490005","brand_name":"Yakima","product_name":"Yakima 1A Raingutter Towers - Set of 4","long_description":"This component of a Yakima car top rack fits virtually any vehicle with a raingutter or driprail.","short_description":"This component of a Yakima car top rack fits virtually any vehicle with a raingutter or driprail.","category":"Car Racks","subcategory":"Base Roof Racks","product_group":"Car Rack Towers","thumb_url":"http://i1.avlws.com/115/s446123.png","image_url":"http://i1.avlws.com/115/l446123.png","buy_link":"http://www.avantlink.com/click.php?p=81603&pw=55475&pt=3&pri=446123&tt=df","retail_price":"195.00","sale_price":"195.00","product_page_view_tracking":"<img src=\"http://www.avantlink.com/dfpv.php?p=81603&amp;pri=446123\" width=\"0\" height=\"0\" style=\"border: none !important; margin: 0px !important;\" alt=\"\" />","medium_image_url":"http://i1.avlws.com/115/m446123.png","product_content_widget":"<script type=\"text/javascript\" src=\"http://www.avantlink.com/apcw.php?mode=5&amp;pw=55475&amp;df=115&amp;sku=490005&amp;link=&amp;tabs=-Details\"></script>","variants":{"4900050016":{"sku":"4900050016","vendor_sku":"8000101","upc":"736745001018","size":"SET OF 4","retail_price":"195.00","sale_price":"195.00"}},"categories":["car-racks","base-roof-racks","car-rack-towers"]}
