{"brand":"Krebs Cycle Products","sku":"678651","brand_name":"Krebs Cycle Products","product_name":"Krebs Cycle Products North San Francisco Bay and Wine Country Bicycle Touring Map","long_description":"This map offers the best bicycle touring routes in Marin, Napa and southern Sonoma Counties with specialized information for fun cycling adventures.","short_description":"This map offers the best bicycle touring routes in Marin, Napa and southern Sonoma Counties with specialized information for fun cycling adventures.","category":"Books And Maps","subcategory":"Maps","product_group":"Paper Maps","thumb_url":"http://i1.avlws.com/115/s409943.png","image_url":"http://i1.avlws.com/115/l409943.png","buy_link":"http://www.avantlink.com/click.php?p=81603&pw=55475&pt=3&pri=409943&tt=df","retail_price":"12.00","sale_price":"12.00","product_page_view_tracking":"<img src=\"http://www.avantlink.com/dfpv.php?p=81603&amp;pri=409943\" width=\"0\" height=\"0\" style=\"border: none !important; margin: 0px !important;\" alt=\"\" />","medium_image_url":"http://i1.avlws.com/115/m409943.png","product_content_widget":"<script type=\"text/javascript\" src=\"http://www.avantlink.com/apcw.php?mode=5&amp;pw=55475&amp;df=115&amp;sku=678651&amp;link=&amp;tabs=-Details\"></script>","variants":{"6786510013":{"sku":"6786510013","vendor_sku":"1891198025","retail_price":"12.00","sale_price":"12.00"}},"categories":["books","maps","paper-maps"]}
