{"sku":"681056","manufacturer_id":"AWS-1","brand_name":"Park Tool","product_name":" Park Hex Wrench - AWS-1","long_description":"Use the Park hardened-steel hex wrench for on-the-road adjustments or at-home repairs. Y shape gives extra leverage for tight Allen bolts. 4, 5, and 6mm hex extensions are vinyl coated for comfort.","short_description":"Use the Park hardened-steel hex wrench for on-the-road adjustments or at-home repairs.","category":"Cycling","subcategory":"Bike Accessories","product_group":"Bike Tools And Maintenance","thumb_url":"http://i1.avlws.com/115/s379127.png","image_url":"http://i1.avlws.com/115/l379127.png","buy_link":"http://www.avantlink.com/click.php?p=81603&pw=55475&pt=3&pri=379127&tt=df","retail_price":"10.00","sale_price":"10.00","product_page_view_tracking":"<img src=\"http://www.avantlink.com/dfpv.php?p=81603&amp;pri=379127\" width=\"0\" height=\"0\" style=\"border: none !important; margin: 0px !important;\" alt=\"\" />","medium_image_url":"http://i1.avlws.com/115/m379127.png","product_content_widget":"<script type=\"text/javascript\" src=\"http://www.avantlink.com/apcw.php?mode=5&amp;pw=55475&amp;df=115&amp;sku=681056&amp;link=&amp;tabs=-Details\"></script>","variants":{"6810560018":{"sku":"6810560018","vendor_sku":"AWS-1","upc":"763477000217","retail_price":"10.00","sale_price":"10.00"}},"categories":["cycling","bike-accessories","bike-tools-and-maintenance"]}
