{"brand":"Merrell","sku":"748502","brand_name":"Merrell","product_name":"Merrell Phaser Peak Hiking Boots - Men's","long_description":"These Phasers will stun you with amazing comfort, rugged durability and solid support--built for long day hikes or weekend backpacking escapes.","short_description":"These Phasers will stun you with amazing comfort, rugged durability and solid support--built for long day hikes or weekend backpacking escapes.","category":"Footwear","subcategory":"Men's Footwear","product_group":"Men's Boots","thumb_url":"http://i1.avlws.com/115/s385047.png","image_url":"http://i1.avlws.com/115/l385047.png","buy_link":"http://www.avantlink.com/click.php?p=81603&pw=55475&pt=3&pri=385047&tt=df","retail_price":"170.00","sale_price":"170.00","product_page_view_tracking":"<img src=\"http://www.avantlink.com/dfpv.php?p=81603&amp;pri=385047\" width=\"0\" height=\"0\" style=\"border: none !important; margin: 0px !important;\" alt=\"\" />","medium_image_url":"http://i1.avlws.com/115/m385047.png","product_content_widget":"<script type=\"text/javascript\" src=\"http://www.avantlink.com/apcw.php?mode=5&amp;pw=55475&amp;df=115&amp;sku=748502&amp;link=&amp;tabs=-Details\"></script>","variants":{"7485020015":{"sku":"7485020015","vendor_sku":"53683","upc":"018461509758","size":"8","color":"Dark Brown","retail_price":"170.00","sale_price":"170.00"},"7485020023":{"sku":"7485020023","vendor_sku":"53683","upc":"018461509765","size":"8.5","color":"Dark Brown","retail_price":"170.00","sale_price":"170.00"},"7485020031":{"sku":"7485020031","vendor_sku":"53683","upc":"018461509772","size":"9","color":"Dark Brown","retail_price":"170.00","sale_price":"170.00"},"7485020049":{"sku":"7485020049","vendor_sku":"53683","upc":"018461509789","size":"9.5","color":"Dark Brown","retail_price":"170.00","sale_price":"170.00"},"7485020056":{"sku":"7485020056","vendor_sku":"53683","upc":"018461509796","size":"10","color":"Dark Brown","retail_price":"170.00","sale_price":"170.00"},"7485020064":{"sku":"7485020064","vendor_sku":"53683","upc":"018461509802","size":"10.5","color":"Dark Brown","retail_price":"170.00","sale_price":"170.00"},"7485020072":{"sku":"7485020072","vendor_sku":"53683","upc":"018461509901","size":"11","color":"Dark Brown","retail_price":"170.00","sale_price":"170.00"},"7485020080":{"sku":"7485020080","vendor_sku":"53683","upc":"018461543233","size":"11.5","color":"Dark Brown","retail_price":"170.00","sale_price":"170.00"},"7485020098":{"sku":"7485020098","vendor_sku":"53683","upc":"018461543240","size":"12","color":"Dark Brown","retail_price":"170.00","sale_price":"170.00"},"7485020106":{"sku":"7485020106","vendor_sku":"53683","upc":"018461543264","size":"13","color":"Dark Brown","retail_price":"170.00","sale_price":"170.00"},"7485020114":{"sku":"7485020114","vendor_sku":"53683","upc":"018461543271","size":"14","color":"Dark Brown","retail_price":"170.00","sale_price":"170.00"}},"categories":["footwear","mens-footwear","mens-boots"]}
