{"sku":"752654","manufacturer_id":"39-651","brand_name":"Spenco","product_name":"Spenco Full-Length Gel Insoles","long_description":"Give your feet a break with these full-length Spenco gel insoles that combine superior cushioning and energy return. Dual-density polyurethane gels and thermoplastic rubber absorb shock and return energy back to your feet. Low-friction top cloth helps reduce blisters and calluses and is treated with an antimicrobial agent to help control odor. Heel cupping provides extra cushion and stability for the heels. Slip-resistant materials keep insoles in place. Replaces original insoles or may be used on top of existing footbeds-trim to fit.","short_description":"Give your feet a break with these full-length Spenco gel insoles that combine superior cushioning and energy return.","category":"Footwear","subcategory":"Footwear Accessories","product_group":"Insoles","thumb_url":"http://i1.avlws.com/115/s376639.png","image_url":"http://i1.avlws.com/115/l376639.png","buy_link":"http://www.avantlink.com/click.php?p=81603&pw=55475&pt=3&pri=376639&tt=df","keywords":"shoe inserts","retail_price":"16.00","sale_price":"16.00","product_page_view_tracking":"<img src=\"http://www.avantlink.com/dfpv.php?p=81603&amp;pri=376639\" width=\"0\" height=\"0\" style=\"border: none !important; margin: 0px !important;\" alt=\"\" />","medium_image_url":"http://i1.avlws.com/115/m376639.png","product_content_widget":"<script type=\"text/javascript\" src=\"http://www.avantlink.com/apcw.php?mode=5&amp;pw=55475&amp;df=115&amp;sku=752654&amp;link=&amp;tabs=-Details\"></script>","variants":{"7526540021":{"sku":"7526540021","vendor_sku":"39-651","upc":"038472795421","size":"2","color":"BLUE","retail_price":"16.00","sale_price":"16.00"},"7526540039":{"sku":"7526540039","vendor_sku":"39-651","upc":"038472795438","size":"3","color":"BLUE","retail_price":"16.00","sale_price":"16.00"},"7526540047":{"sku":"7526540047","vendor_sku":"39-651","upc":"038472795445","size":"4","color":"BLUE","retail_price":"16.00","sale_price":"16.00"},"7526540054":{"sku":"7526540054","vendor_sku":"39-651","upc":"038472795452","size":"5","color":"BLUE","retail_price":"16.00","sale_price":"16.00"}},"categories":["footwear","footwear-accessories","insoles"]}
