{"brand":"Shimano","sku":"778833","brand_name":"Shimano","product_name":"Shimano XT M770 Chainring 104mm - 32 Teeth","long_description":"Replace your worn middle chainring with this Shimano Deore XT M770 ring to revitalize your drivetrain.","short_description":"Replace your worn middle chainring with this Shimano Deore XT M770 ring to revitalize your drivetrain.","category":"Cycling","subcategory":"Bike Components","product_group":"Drivetrain Components","thumb_url":"http://i1.avlws.com/115/s390019.png","image_url":"http://i1.avlws.com/115/l390019.png","buy_link":"http://www.avantlink.com/click.php?p=81603&pw=55475&pt=3&pri=390019&tt=df","retail_price":"49.00","sale_price":"49.00","product_page_view_tracking":"<img src=\"http://www.avantlink.com/dfpv.php?p=81603&amp;pri=390019\" width=\"0\" height=\"0\" style=\"border: none !important; margin: 0px !important;\" alt=\"\" />","medium_image_url":"http://i1.avlws.com/115/m390019.png","product_content_widget":"<script type=\"text/javascript\" src=\"http://www.avantlink.com/apcw.php?mode=5&amp;pw=55475&amp;df=115&amp;sku=778833&amp;link=&amp;tabs=-Details\"></script>","variants":{"7788330012":{"sku":"7788330012","vendor_sku":"Y1J198020","upc":"689228223455","size":"32 TEETH","retail_price":"49.00","sale_price":"49.00"}},"categories":["cycling","bike-components","drivetrain-components"]}
