{"sku":"796288","manufacturer_id":"HG0127","brand_name":"Humangear","product_name":" humangear GoToob Bottle - 3 fl. oz.","long_description":"The carry-on-approved humangear GoToob 3 fl. oz. bottle makes it easy to travel with your favorite gels and lotions. No-drip valve easily dispenses gels and lotions; large opening is easy to fill and clean, and integrated rubber seal prevents leaks. Bottle features a rotating collar and integrated label so you can mark the contents as conditioner, shampoo, sunblock, lotion or soap; tightening cap locks the collar in place. Bottle is sized to slip easily into pockets, bags, purses and other tight spots. Food-grade silicone bottle and polypropylene cap are 100% BPA free.","short_description":"The carry-on-approved humangear GoToob 3 fl. oz. bottle makes it easy to travel with your favorite gels and lotions.","category":"Camping And Hiking","subcategory":"Water Bottles And Treatment","product_group":"Water Bottles, Flasks And Jugs","thumb_url":"http://i1.avlws.com/115/s425523.png","image_url":"http://i1.avlws.com/115/l425523.png","buy_link":"http://www.avantlink.com/click.php?p=81603&pw=55475&pt=3&pri=425523&tt=df","retail_price":"9.95","sale_price":"9.95","product_page_view_tracking":"<img src=\"http://www.avantlink.com/dfpv.php?p=81603&amp;pri=425523\" width=\"0\" height=\"0\" style=\"border: none !important; margin: 0px !important;\" alt=\"\" />","medium_image_url":"http://i1.avlws.com/115/m425523.png","product_content_widget":"<script type=\"text/javascript\" src=\"http://www.avantlink.com/apcw.php?mode=5&amp;pw=55475&amp;df=115&amp;sku=796288&amp;link=&amp;tabs=-Details\"></script>","variants":{"7962880014":{"sku":"7962880014","vendor_sku":"HG0107","upc":"649241880950","color":"CLEAR","retail_price":"9.95","sale_price":"9.95"},"7962880022":{"sku":"7962880022","vendor_sku":"HG0137","upc":"649241880981","color":"HOT PINK","retail_price":"9.95","sale_price":"9.95"},"7962880030":{"sku":"7962880030","vendor_sku":"HG0117","upc":"649241880967","color":"LIME GREEN","retail_price":"9.95","sale_price":"9.95"},"7962880048":{"sku":"7962880048","vendor_sku":"HG0127","upc":"649241880974","color":"SKY BLUE","retail_price":"9.95","sale_price":"9.95"},"7962880055":{"sku":"7962880055","vendor_sku":"HG0147","upc":"649241886365","color":"ORANGE","retail_price":"9.95","sale_price":"9.95"}},"categories":["camping-hiking","water-bottles-and-treatment","water-bottles-flasks-and-jugs"]}
