{"sku":"807710","manufacturer_id":"WS1121","brand_name":"Bob","product_name":" BOB Sun Shield Cover - Single","long_description":"The BOB Sun Shield cover helps reduce exposure to harmful ultraviolet rays (UVA/UVB) and also protects children from wind and flying insects. Main front panel is constructed of protective mesh that allows children to see out and parents to see in. The rest of the Sun Shield cover is constructed out of sturdy nylon for lasting use. Elastic attachment is simple and easy. Fits BOB single strollers.","short_description":"The BOB Sun Shield cover helps reduce exposure to harmful ultraviolet rays (UVA/UVB) and also protects children from wind and flying insects.","category":"Fitness","subcategory":"Running","product_group":"Strollers","thumb_url":"http://i1.avlws.com/115/s427419.png","image_url":"http://i1.avlws.com/115/l427419.png","buy_link":"http://www.avantlink.com/click.php?p=81603&pw=55475&pt=3&pri=427419&tt=df","retail_price":"69.00","sale_price":"69.00","product_page_view_tracking":"<img src=\"http://www.avantlink.com/dfpv.php?p=81603&amp;pri=427419\" width=\"0\" height=\"0\" style=\"border: none !important; margin: 0px !important;\" alt=\"\" />","medium_image_url":"http://i1.avlws.com/115/m427419.png","product_content_widget":"<script type=\"text/javascript\" src=\"http://www.avantlink.com/apcw.php?mode=5&amp;pw=55475&amp;df=115&amp;sku=807710&amp;link=&amp;tabs=-Details\"></script>","variants":{"8077100017":{"sku":"8077100017","vendor_sku":"WS1121","upc":"692176705485","color":"GRAY","retail_price":"69.00","sale_price":"69.00"}}}
