{"brand":"Pearl Izumi","sku":"837216","brand_name":"Pearl Izumi","product_name":"Pearl Izumi Elite Thermal Knee Warmers","long_description":"With the Pearl Izumi Elite Thermal knee warmers, you can be ready for the cold at a moment's notice.","short_description":"With the Pearl Izumi Elite Thermal knee warmers, you can be ready for the cold at a moment's notice.","category":"Cycling","subcategory":"Cycling Clothing","product_group":"Cycling Clothing Accessories","thumb_url":"http://i1.avlws.com/115/s391167.png","image_url":"http://i1.avlws.com/115/l391167.png","buy_link":"http://www.avantlink.com/click.php?p=81603&pw=55475&pt=3&pri=391167&tt=df","retail_price":"40.00","sale_price":"40.00","product_page_view_tracking":"<img src=\"http://www.avantlink.com/dfpv.php?p=81603&amp;pri=391167\" width=\"0\" height=\"0\" style=\"border: none !important; margin: 0px !important;\" alt=\"\" />","medium_image_url":"http://i1.avlws.com/115/m391167.png","product_content_widget":"<script type=\"text/javascript\" src=\"http://www.avantlink.com/apcw.php?mode=5&amp;pw=55475&amp;df=115&amp;sku=837216&amp;link=&amp;tabs=-Details\"></script>","variants":{"8372160001":{"sku":"8372160001","vendor_sku":"14371209021S","upc":"703051896058","size":"S","color":"Black","retail_price":"40.00","sale_price":"40.00"},"8372160002":{"sku":"8372160002","vendor_sku":"14371209021M","upc":"703051896041","size":"M","color":"Black","retail_price":"40.00","sale_price":"40.00"},"8372160003":{"sku":"8372160003","vendor_sku":"14371209021L","upc":"703051896034","size":"L","color":"Black","retail_price":"40.00","sale_price":"40.00"},"8372160004":{"sku":"8372160004","vendor_sku":"14371209021XL","upc":"703051896065","size":"XL","color":"Black","retail_price":"40.00","sale_price":"40.00"}},"categories":["cycling","cycling-clothing","cycling-clothing-accessories"]}
