{"brand":"O'neill","sku":"850515","brand_name":"O'neill","product_name":"O'Neill Skins RG8 Crew Rashguard - Women's","long_description":"Featuring high recycled content, the women's O'Neill Skins RG8 crew rashguard brings soft, quick-drying comfort to your day on the water.","short_description":"Featuring high recycled content, the women's O'Neill Skins RG8 crew rashguard brings soft, quick-drying comfort to your day on the water.","category":"Women's Clothing","subcategory":"Women's Shirts","product_group":"Women's Rashguards","thumb_url":"http://i1.avlws.com/115/s396815.png","image_url":"http://i1.avlws.com/115/l396815.png","buy_link":"http://www.avantlink.com/click.php?p=81603&pw=55475&pt=3&pri=396815&tt=df","retail_price":"24.83","sale_price":"24.83","product_page_view_tracking":"<img src=\"http://www.avantlink.com/dfpv.php?p=81603&amp;pri=396815\" width=\"0\" height=\"0\" style=\"border: none !important; margin: 0px !important;\" alt=\"\" />","medium_image_url":"http://i1.avlws.com/115/m396815.png","product_content_widget":"<script type=\"text/javascript\" src=\"http://www.avantlink.com/apcw.php?mode=5&amp;pw=55475&amp;df=115&amp;sku=850515&amp;link=&amp;tabs=-Details\"></script>","variants":{"8505150007":{"sku":"8505150007","vendor_sku":"3916-216","upc":"603731986393","size":"L","color":"Light Aqua","retail_price":"24.83","sale_price":"24.83"},"8505150008":{"sku":"8505150008","vendor_sku":"3916-216","upc":"603731986454","size":"XL","color":"Light Aqua","retail_price":"24.83","sale_price":"24.83"}},"categories":["womens","womens-shirts","womens-rashguards"]}
