{"sku":"851063","manufacturer_id":"BO-ZAFU-CHOICE-","brand_name":"Hugger Mugger","product_name":" Hugger Mugger Zafu Meditation Cushion","long_description":"The Hugger Mugger Zafu Meditation cushion supports cross-legged, seated and kneeling positions so you can meditate in comfort. Traditional round shape features buckwheat hull filling that conforms to the shape of your body and is extremely resilient. Zippered cover allows you to add or remove filling to customize the cushion.","short_description":"The Hugger Mugger Zafu Meditation cushion supports cross-legged, seated and kneeling positions so you can meditate in comfort.","category":"Fitness","subcategory":"Yoga","product_group":"Yoga Props","thumb_url":"http://i1.avlws.com/115/s428039.png","image_url":"http://i1.avlws.com/115/l428039.png","buy_link":"http://www.avantlink.com/click.php?p=81603&pw=55475&pt=3&pri=428039&tt=df","retail_price":"46.95","sale_price":"46.95","product_page_view_tracking":"<img src=\"http://www.avantlink.com/dfpv.php?p=81603&amp;pri=428039\" width=\"0\" height=\"0\" style=\"border: none !important; margin: 0px !important;\" alt=\"\" />","medium_image_url":"http://i1.avlws.com/115/m428039.png","product_content_widget":"<script type=\"text/javascript\" src=\"http://www.avantlink.com/apcw.php?mode=5&amp;pw=55475&amp;df=115&amp;sku=851063&amp;link=&amp;tabs=-Details\"></script>","variants":{"8510630001":{"sku":"8510630001","vendor_sku":"BO-ZAFU-CHOICE-","upc":"803410550352","size":"15 IN","color":"PLUM","retail_price":"46.95","sale_price":"46.95"}},"categories":["fitness","yoga","yoga-props"]}
