{"sku":"855335","manufacturer_id":"ID10REISM","brand_name":"Rei","product_name":"REI Aluminum ID Tag","long_description":"The REI Aluminum ID Tag has a modern style that easily identifies your luggage on the airport carousel while keeping your personal information hidden from the public. Tag is made from durable aluminum; coated stainless steel cable keeps the Aluminum ID Tag securely attached to your bag.","short_description":"The REI Aluminum ID Tag has a modern style that easily identifies your luggage on the airport carousel while keeping your personal information hidden from the public.","category":"Travel And Luggage","subcategory":"Luggage","product_group":"Luggage Accessories","thumb_url":"http://i1.avlws.com/115/s433547.png","image_url":"http://i1.avlws.com/115/l433547.png","buy_link":"http://www.avantlink.com/click.php?p=81603&pw=55475&pt=3&pri=433547&tt=df","retail_price":"7.50","sale_price":"7.50","product_page_view_tracking":"<img src=\"http://www.avantlink.com/dfpv.php?p=81603&amp;pri=433547\" width=\"0\" height=\"0\" style=\"border: none !important; margin: 0px !important;\" alt=\"\" />","medium_image_url":"http://i1.avlws.com/115/m433547.png","product_content_widget":"<script type=\"text/javascript\" src=\"http://www.avantlink.com/apcw.php?mode=5&amp;pw=55475&amp;df=115&amp;sku=855335&amp;link=&amp;tabs=-Details\"></script>","variants":{"8553350001":{"sku":"8553350001","vendor_sku":"ID10REISM","upc":"029275310706","color":"SMOKE","retail_price":"7.50","sale_price":"7.50"},"8553350002":{"sku":"8553350002","vendor_sku":"ID10REIGR","upc":"029275310713","color":"LIGHT GREEN","retail_price":"4.93","sale_price":"4.93"},"8553350003":{"sku":"8553350003","vendor_sku":"ID10REIOR","upc":"029275310720","color":"BURNT ORANGE","retail_price":"4.93","sale_price":"4.93"}}}
