{"brand":"Osprey","sku":"855636","brand_name":"Osprey","product_name":"Osprey Kode 22 Snow Pack","long_description":"Incorporating feedback from backcountry professionals and athletes, the redesigned Osprey Kode 22 ski pack offers logical organization and sharp style for riders seeking quick off-piste forays.","short_description":"Incorporating feedback from backcountry professionals and athletes, the redesigned Osprey Kode 22 ski pack offers logical organization and sharp style for riders seeking quick off-piste forays.","category":"Skiing","subcategory":"Ski Packs And Bags","product_group":"Ski Packs","thumb_url":"http://i1.avlws.com/115/s342019.png","image_url":"http://i1.avlws.com/115/l342019.png","buy_link":"http://www.avantlink.com/click.php?p=81603&pw=55475&pt=3&pri=342019&tt=df","retail_price":"129.95","sale_price":"129.95","product_page_view_tracking":"<img src=\"http://www.avantlink.com/dfpv.php?p=81603&amp;pri=342019\" width=\"0\" height=\"0\" style=\"border: none !important; margin: 0px !important;\" alt=\"\" />","medium_image_url":"http://i1.avlws.com/115/m342019.png","product_content_widget":"<script type=\"text/javascript\" src=\"http://www.avantlink.com/apcw.php?mode=5&amp;pw=55475&amp;df=115&amp;sku=855636&amp;link=&amp;tabs=-Details\"></script>","variants":{"8556360002":{"sku":"8556360002","vendor_sku":"036622-550-2-M/L","upc":"877257020514","size":"M/L","color":"Black","retail_price":"129.95","sale_price":"129.95"},"8556360003":{"sku":"8556360003","vendor_sku":"036622-703-1-S/M","upc":"877257020521","size":"S/M","color":"Nitro Green","retail_price":"129.95","sale_price":"129.95"},"8556360004":{"sku":"8556360004","vendor_sku":"036622-703-2-M/L","upc":"877257020538","size":"M/L","color":"Nitro Green","retail_price":"129.95","sale_price":"129.95"}},"categories":["snow","ski-packs-and-bags","ski-packs"]}
