{"sku":"859697","manufacturer_id":"555090-003","brand_name":"Nike","product_name":"Nike Revolution 2 (GS) Running Shoes - Girls'","long_description":"The girls' Nike Revolution 2 (GS) running shoes will have your young one racing up and down the hills when you head out for a jog together. Lightweight open mesh throughout the uppers enhances breathability and comfort; strategically placed leather overlays offer support. Articulated, full-length Phylon midsoles provide lightweight, responsive cushioning and a natural feel underfoot. Rubber outsoles maximize traction and durability; flex grooves along shoes enhance flexibility for an efficient stride.","short_description":"The girls' Nike Revolution 2 (GS) running shoes will have your young one racing up and down the hills when you head out for a jog together.","category":"Footwear","subcategory":"Kids' Footwear","product_group":"Kids' Shoes","thumb_url":"http://i1.avlws.com/115/s377467.png","image_url":"http://i1.avlws.com/115/l377467.png","buy_link":"http://www.avantlink.com/click.php?p=81603&pw=55475&pt=3&pri=377467&tt=df","retail_price":"50.00","sale_price":"50.00","product_page_view_tracking":"<img src=\"http://www.avantlink.com/dfpv.php?p=81603&amp;pri=377467\" width=\"0\" height=\"0\" style=\"border: none !important; margin: 0px !important;\" alt=\"\" />","medium_image_url":"http://i1.avlws.com/115/m377467.png","product_content_widget":"<script type=\"text/javascript\" src=\"http://www.avantlink.com/apcw.php?mode=5&amp;pw=55475&amp;df=115&amp;sku=859697&amp;link=&amp;tabs=-Details\"></script>","variants":{"8596970001":{"sku":"8596970001","vendor_sku":"555090-003","upc":"887225090722","size":"Kids 4","color":"BLACK/PINK FOIL/METALLIC","retail_price":"50.00","sale_price":"50.00"},"8596970002":{"sku":"8596970002","vendor_sku":"555090-003","upc":"887225090739","size":"Kids 4.5","color":"BLACK/PINK FOIL/METALLIC","retail_price":"50.00","sale_price":"50.00"},"8596970003":{"sku":"8596970003","vendor_sku":"555090-003","upc":"887225090746","size":"Kids 5","color":"BLACK/PINK FOIL/METALLIC","retail_price":"50.00","sale_price":"50.00"},"8596970004":{"sku":"8596970004","vendor_sku":"555090-003","upc":"887225090753","size":"Kids 5.5","color":"BLACK/PINK FOIL/METALLIC","retail_price":"50.00","sale_price":"50.00"},"8596970005":{"sku":"8596970005","vendor_sku":"555090-003","upc":"887225090760","size":"Kids 6","color":"BLACK/PINK FOIL/METALLIC","retail_price":"50.00","sale_price":"50.00"},"8596970006":{"sku":"8596970006","vendor_sku":"555090-401","upc":"659658712416","size":"Kids 4","color":"POLARIZED BLUE/WHITE/CRIM","retail_price":"50.00","sale_price":"50.00"},"8596970007":{"sku":"8596970007","vendor_sku":"555090-401","upc":"659658712430","size":"Kids 4.5","color":"POLARIZED BLUE/WHITE/CRIM","retail_price":"50.00","sale_price":"50.00"},"8596970008":{"sku":"8596970008","vendor_sku":"555090-401","upc":"659658712447","size":"Kids 5","color":"POLARIZED BLUE/WHITE/CRIM","retail_price":"50.00","sale_price":"50.00"},"8596970009":{"sku":"8596970009","vendor_sku":"555090-401","upc":"659658712454","size":"Kids 5.5","color":"POLARIZED BLUE/WHITE/CRIM","retail_price":"50.00","sale_price":"50.00"},"8596970010":{"sku":"8596970010","vendor_sku":"555090-401","upc":"659658712461","size":"Kids 6","color":"POLARIZED BLUE/WHITE/CRIM","retail_price":"50.00","sale_price":"50.00"}},"categories":["footwear","kids-footwear","kids-shoes"]}
