{"sku":"867577","manufacturer_id":"7042329","brand_name":"Giro","product_name":"Giro Civila Bike Shoes - Women's","long_description":"Giro Civila Bike Shoes for women provide comfort as you ride, and style and walking traction when you get to your destination. High-quality, perforated microfiber uppers feature nonslip laces and a micro-suede heel counter. Injected nylon outsoles have a 2-bolt cleat mount, replaceable high-traction walking pads and scuff guards at midfoot. Molded EVA footbeds provide a microsuede topsheet and medium arch support. Antimicrobial treatment in the Giro Civila Bike Shoes for women helps manage odor.","short_description":"Giro Civila Bike Shoes for women provide comfort as you ride, and style and walking traction when you get to your destination.","category":"Cycling","subcategory":"Cycling Shoes","product_group":"Mountain Bike Shoes","thumb_url":"http://i1.avlws.com/115/s380439.png","image_url":"http://i1.avlws.com/115/l380439.png","buy_link":"http://www.avantlink.com/click.php?p=81603&pw=55475&pt=3&pri=380439&tt=df","retail_price":"150.00","sale_price":"150.00","product_page_view_tracking":"<img src=\"http://www.avantlink.com/dfpv.php?p=81603&amp;pri=380439\" width=\"0\" height=\"0\" style=\"border: none !important; margin: 0px !important;\" alt=\"\" />","medium_image_url":"http://i1.avlws.com/115/m380439.png","product_content_widget":"<script type=\"text/javascript\" src=\"http://www.avantlink.com/apcw.php?mode=5&amp;pw=55475&amp;df=115&amp;sku=867577&amp;link=&amp;tabs=-Details\"></script>","variants":{"8675770004":{"sku":"8675770004","vendor_sku":"7042326","upc":"768686982460","size":"39","color":"BLACK/WHITE/MILKY BLUE","retail_price":"150.00","sale_price":"150.00"},"8675770005":{"sku":"8675770005","vendor_sku":"7042327","upc":"768686982477","size":"40","color":"BLACK/WHITE/MILKY BLUE","retail_price":"150.00","sale_price":"150.00"}},"categories":["cycling","cycling-shoes","mountain-bike-shoes"]}
