{"brand":"Rei","sku":"870150","brand_name":"Rei","product_name":"REI Midweight Long Underwear Half-Zip Shirt - Men's Tall","long_description":"Excellent flexibility and moisture control make the men's tall REI Midweight Long Underwear Half-Zip Shirt an outstanding choice for a wide range of activities in cool conditions.","short_description":"Excellent flexibility and moisture control make the men's tall REI Midweight Long Underwear Half-Zip Shirt an outstanding choice for a wide range of activities in cool conditions.","category":"Men's Clothing","subcategory":"Men's Underwear","product_group":"Men's Long Underwear Tops","thumb_url":"http://i1.avlws.com/115/s477343.png","image_url":"http://i1.avlws.com/115/l477343.png","buy_link":"http://www.avantlink.com/click.php?p=81603&pw=55475&pt=3&pri=477343&tt=df","retail_price":"49.50","sale_price":"49.50","product_page_view_tracking":"<img src=\"http://www.avantlink.com/dfpv.php?p=81603&amp;pri=477343\" width=\"0\" height=\"0\" style=\"border: none !important; margin: 0px !important;\" alt=\"\" />","medium_image_url":"http://i1.avlws.com/115/m477343.png","product_content_widget":"<script type=\"text/javascript\" src=\"http://www.avantlink.com/apcw.php?mode=5&amp;pw=55475&amp;df=115&amp;sku=870150&amp;link=&amp;tabs=-Details\"></script>","variants":{"8701500001":{"sku":"8701500001","vendor_sku":"16665","upc":"487015000018","size":"M TALL","color":"Copper Spice","retail_price":"23.83","sale_price":"23.83"},"8701500002":{"sku":"8701500002","vendor_sku":"16665","upc":"487015000025","size":"L TALL","color":"Copper Spice","retail_price":"23.83","sale_price":"23.83"},"8701500003":{"sku":"8701500003","vendor_sku":"16665","upc":"487015000032","size":"XL TALL","color":"Copper Spice","retail_price":"23.83","sale_price":"23.83"},"8701500004":{"sku":"8701500004","vendor_sku":"16665","upc":"487015000049","size":"M TALL","color":"Olive Branch","retail_price":"49.50","sale_price":"49.50"},"8701500005":{"sku":"8701500005","vendor_sku":"16665","upc":"487015000056","size":"L TALL","color":"Olive Branch","retail_price":"49.50","sale_price":"49.50"},"8701500006":{"sku":"8701500006","vendor_sku":"16665","upc":"487015000063","size":"XL TALL","color":"Olive Branch","retail_price":"49.50","sale_price":"49.50"}},"categories":["mens","mens-underwear","mens-long-underwear-tops"]}
