{"brand":"Toad&Co","sku":"871423","brand_name":"Toad&Co","product_name":"Toad&Co Drover Denim Pants - Men's 30\" Inseam","long_description":"A modern take on the classic denim blue jean, the Horny Toad Drover Denim Pants with 30-in. inseam combine organic cotton and spandex for stretch that you'll love on your urban adventures.","short_description":"A modern take on the classic denim blue jean, the Horny Toad Drover Denim Pants with 30-in. inseam combine organic cotton and spandex for stretch that you'll love on your urban adventures.","category":"Men's Clothing","subcategory":"Men's Pants","product_group":"Men's Casual Pants","thumb_url":"http://i1.avlws.com/115/s472423.png","image_url":"http://i1.avlws.com/115/l472423.png","buy_link":"http://www.avantlink.com/click.php?p=81603&pw=55475&pt=3&pri=472423&tt=df","retail_price":"43.83","sale_price":"43.83","product_page_view_tracking":"<img src=\"http://www.avantlink.com/dfpv.php?p=81603&amp;pri=472423\" width=\"0\" height=\"0\" style=\"border: none !important; margin: 0px !important;\" alt=\"\" />","medium_image_url":"http://i1.avlws.com/115/m472423.png","product_content_widget":"<script type=\"text/javascript\" src=\"http://www.avantlink.com/apcw.php?mode=5&amp;pw=55475&amp;df=115&amp;sku=871423&amp;link=&amp;tabs=-Details\"></script>","variants":{"8714230004":{"sku":"8714230004","vendor_sku":"H2441404 406 36","upc":"882923747800","size":"36","color":"Dark Denim","retail_price":"43.83","sale_price":"43.83"},"8714230005":{"sku":"8714230005","vendor_sku":"H2441404 406 38","upc":"882923747817","size":"38","color":"Dark Denim","retail_price":"43.83","sale_price":"43.83"},"8714230008":{"sku":"8714230008","vendor_sku":"H2441404 409 34","upc":"882923747848","size":"34","color":"Medium Denim","retail_price":"43.83","sale_price":"43.83"},"8714230009":{"sku":"8714230009","vendor_sku":"H2441404 409 36","upc":"882923747855","size":"36","color":"Medium Denim","retail_price":"43.83","sale_price":"43.83"}},"categories":["mens","mens-pants","mens-casual-pants"]}
