{"sku":"873653","brand_name":"The North Face","product_name":"The North Face Slasher Cargo Shell Pants - Men's - 2013 Closout","long_description":"The North Face Slasher Cargo Shell Pants for men offer workwear-inspired durability with waterproof, breathable protection for your first-tracks, last-chair fun season after season.","short_description":"The North Face Slasher Cargo Shell Pants for men offer workwear-inspired durability with waterproof, breathable protection for your first-tracks, last-chair fun season after season.","category":"Men's Clothing","subcategory":"Men's Pants","product_group":"Men's Snow Pants","thumb_url":"http://i1.avlws.com/115/s468295.png","image_url":"http://i1.avlws.com/115/l468295.png","buy_link":"http://www.avantlink.com/click.php?p=81603&pw=55475&pt=3&pri=468295&tt=df","retail_price":"119.73","sale_price":"119.73","product_page_view_tracking":"<img src=\"http://www.avantlink.com/dfpv.php?p=81603&amp;pri=468295\" width=\"0\" height=\"0\" style=\"border: none !important; margin: 0px !important;\" alt=\"\" />","medium_image_url":"http://i1.avlws.com/115/m468295.png","product_content_widget":"<script type=\"text/javascript\" src=\"http://www.avantlink.com/apcw.php?mode=5&amp;pw=55475&amp;df=115&amp;sku=873653&amp;link=&amp;tabs=-Details\"></script>","variants":{"8736530001":{"sku":"8736530001","vendor_sku":"A7FAD6R","upc":"487365300011","size":"S","color":"Majestic Red","retail_price":"119.73","sale_price":"119.73"},"8736530002":{"sku":"8736530002","vendor_sku":"A7FAD6R","upc":"487365300028","size":"M","color":"Majestic Red","retail_price":"119.73","sale_price":"119.73"},"8736530003":{"sku":"8736530003","vendor_sku":"A7FAD6R","upc":"487365300035","size":"L","color":"Majestic Red","retail_price":"119.73","sale_price":"119.73"},"8736530004":{"sku":"8736530004","vendor_sku":"A7FAD6R","upc":"487365300042","size":"XL","color":"Majestic Red","retail_price":"119.73","sale_price":"119.73"},"8736530005":{"sku":"8736530005","vendor_sku":"A7FAD6R","upc":"487365300059","size":"XXL","color":"Majestic Red","retail_price":"119.73","sale_price":"119.73"},"8736530006":{"sku":"8736530006","vendor_sku":"A7FAD9S","upc":"808390938428","size":"S","color":"Seal Brown","retail_price":"119.73","sale_price":"119.73"},"8736530007":{"sku":"8736530007","vendor_sku":"A7FAD9S","upc":"808390938404","size":"M","color":"Seal Brown","retail_price":"119.73","sale_price":"119.73"},"8736530008":{"sku":"8736530008","vendor_sku":"A7FAD9S","upc":"808390938367","size":"L","color":"Seal Brown","retail_price":"119.73","sale_price":"119.73"},"8736530009":{"sku":"8736530009","vendor_sku":"A7FAD9S","upc":"808390937193","size":"XL","color":"Seal Brown","retail_price":"119.73","sale_price":"119.73"},"8736530010":{"sku":"8736530010","vendor_sku":"A7FAD9S","upc":"808390938329","size":"XXL","color":"Seal Brown","retail_price":"119.73","sale_price":"119.73"},"8736530011":{"sku":"8736530011","vendor_sku":"A7FAE4F","upc":"808390971197","size":"S","color":"Pavilion Green","retail_price":"119.73","sale_price":"119.73"},"8736530012":{"sku":"8736530012","vendor_sku":"A7FAE4F","upc":"808390971227","size":"M","color":"Pavilion Green","retail_price":"119.73","sale_price":"119.73"},"8736530013":{"sku":"8736530013","vendor_sku":"A7FAE4F","upc":"808390971166","size":"L","color":"Pavilion Green","retail_price":"119.73","sale_price":"119.73"},"8736530014":{"sku":"8736530014","vendor_sku":"A7FAE4F","upc":"808390970725","size":"XL","color":"Pavilion Green","retail_price":"119.73","sale_price":"119.73"},"8736530015":{"sku":"8736530015","vendor_sku":"A7FAE4F","upc":"808390971135","size":"XXL","color":"Pavilion Green","retail_price":"119.73","sale_price":"119.73"},"8736530016":{"sku":"8736530016","vendor_sku":"A7FAF2S","upc":"808390971357","size":"S","color":"New Taupe Green Woodland","retail_price":"119.73","sale_price":"119.73"},"8736530017":{"sku":"8736530017","vendor_sku":"A7FAF2S","upc":"808390971449","size":"M","color":"New Taupe Green Woodland","retail_price":"119.73","sale_price":"119.73"},"8736530018":{"sku":"8736530018","vendor_sku":"A7FAF2S","upc":"808390971326","size":"L","color":"New Taupe Green Woodland","retail_price":"119.73","sale_price":"119.73"},"8736530019":{"sku":"8736530019","vendor_sku":"A7FAF2S","upc":"808390971234","size":"XL","color":"New Taupe Green Woodland","retail_price":"119.73","sale_price":"119.73"},"8736530020":{"sku":"8736530020","vendor_sku":"A7FAF2S","upc":"808390971296","size":"XXL","color":"New Taupe Green Woodland","retail_price":"119.73","sale_price":"119.73"},"8736530021":{"sku":"8736530021","vendor_sku":"A7FA173","upc":"487365300219","size":"S","color":"Utility Brown","retail_price":"119.73","sale_price":"119.73"},"8736530022":{"sku":"8736530022","vendor_sku":"A7FA173","upc":"487365300226","size":"M","color":"Utility Brown","retail_price":"119.73","sale_price":"119.73"},"8736530023":{"sku":"8736530023","vendor_sku":"A7FA173","upc":"487365300233","size":"L","color":"Utility Brown","retail_price":"119.73","sale_price":"119.73"},"8736530024":{"sku":"8736530024","vendor_sku":"A7FA173","upc":"487365300240","size":"XL","color":"Utility Brown","retail_price":"119.73","sale_price":"119.73"},"8736530025":{"sku":"8736530025","vendor_sku":"A7FA173","upc":"487365300257","size":"XXL","color":"Utility Brown","retail_price":"119.73","sale_price":"119.73"},"8736530026":{"sku":"8736530026","vendor_sku":"A7FA21L","upc":"487365300264","size":"S","color":"New Taupe Green","retail_price":"119.73","sale_price":"119.73"},"8736530027":{"sku":"8736530027","vendor_sku":"A7FA21L","upc":"487365300271","size":"M","color":"New Taupe Green","retail_price":"119.73","sale_price":"119.73"},"8736530028":{"sku":"8736530028","vendor_sku":"A7FA21L","upc":"487365300288","size":"L","color":"New Taupe Green","retail_price":"119.73","sale_price":"119.73"},"8736530029":{"sku":"8736530029","vendor_sku":"A7FA21L","upc":"487365300295","size":"XL","color":"New Taupe Green","retail_price":"119.73","sale_price":"119.73"},"8736530030":{"sku":"8736530030","vendor_sku":"A7FA21L","upc":"487365300301","size":"XXL","color":"New Taupe Green","retail_price":"119.73","sale_price":"119.73"},"8736530031":{"sku":"8736530031","vendor_sku":"A7FAA4M","upc":"808390970374","size":"S","color":"Nautical Blue","retail_price":"119.73","sale_price":"119.73"},"8736530032":{"sku":"8736530032","vendor_sku":"A7FAA4M","upc":"808390970404","size":"M","color":"Nautical Blue","retail_price":"119.73","sale_price":"119.73"},"8736530033":{"sku":"8736530033","vendor_sku":"A7FAA4M","upc":"808390970343","size":"L","color":"Nautical Blue","retail_price":"119.73","sale_price":"119.73"},"8736530034":{"sku":"8736530034","vendor_sku":"A7FAA4M","upc":"808390969637","size":"XL","color":"Nautical Blue","retail_price":"119.73","sale_price":"119.73"},"8736530035":{"sku":"8736530035","vendor_sku":"A7FAA4M","upc":"808390970312","size":"XXL","color":"Nautical Blue","retail_price":"119.73","sale_price":"119.73"}},"categories":["mens","mens-pants","mens-snow-pants"]}
