{"sku":"876272","manufacturer_id":"WO-CF-45051","brand_name":"Woods","product_name":" Woods Aluminum Double Roll-Up Table - 2012 Closeout","long_description":"The Woods Aluminum Double Roll-Up Table collapses down and stows in an included carrying case, making it easy to take along on car-camping trips and picnics in the park. Adjustable leg length lets you level the table on uneven ground. Includes an extra storage compartment under the table. The Woods Aluminum Double Roll-Up Table folds down and fits in the included carrying case. Closeout.","short_description":"The Woods Aluminum Double Roll-Up Table collapses down and stows in an included carrying case, making it easy to take along on car-camping trips and picnics in the park.","category":"Camping And Hiking","subcategory":"Camp Furniture","product_group":"Camp Tables","thumb_url":"http://i1.avlws.com/115/s456283.png","image_url":"http://i1.avlws.com/115/l456283.png","buy_link":"http://www.avantlink.com/click.php?p=81603&pw=55475&pt=3&pri=456283&tt=df","retail_price":"120.00","sale_price":"79.73","product_page_view_tracking":"<img src=\"http://www.avantlink.com/dfpv.php?p=81603&amp;pri=456283\" width=\"0\" height=\"0\" style=\"border: none !important; margin: 0px !important;\" alt=\"\" />","medium_image_url":"http://i1.avlws.com/115/m456283.png","product_content_widget":"<script type=\"text/javascript\" src=\"http://www.avantlink.com/apcw.php?mode=5&amp;pw=55475&amp;df=115&amp;sku=876272&amp;link=&amp;tabs=-Details\"></script>","variants":{"8762720001":{"sku":"8762720001","vendor_sku":"WO-CF-45051","upc":"628547013491","color":"ALUMINUM","retail_price":"79.73","sale_price":"79.73"}},"categories":["camping-hiking","camp-furniture","camp-tables"]}
