{"sku":"878057","brand_name":"Prana","product_name":"prAna Gabi Yoga Leggings - Women's","long_description":"Made with quick-dry stretch fabric and a wide waistband, this two-tone legging flatters while contouring your body as you move, freeing you from distraction for optimal focus on breathing and form.","short_description":"Made with quick-dry stretch fabric and a wide waistband, this two-tone legging flatters while contouring your body as you move, freeing you from distraction for optimal focus on breathing and form.","category":"Women's Clothing","subcategory":"Women's Pants","product_group":"Women's Yoga Pants","thumb_url":"http://i1.avlws.com/115/s523631.png","image_url":"http://i1.avlws.com/115/l523631.png","buy_link":"http://www.avantlink.com/click.php?p=81603&pw=55475&pt=3&pri=523631&tt=df","retail_price":"75.00","sale_price":"75.00","product_page_view_tracking":"<img src=\"http://www.avantlink.com/dfpv.php?p=81603&amp;pri=523631\" width=\"0\" height=\"0\" style=\"border: none !important; margin: 0px !important;\" alt=\"\" />","medium_image_url":"http://i1.avlws.com/115/m523631.png","product_content_widget":"<script type=\"text/javascript\" src=\"http://www.avantlink.com/apcw.php?mode=5&amp;pw=55475&amp;df=115&amp;sku=878057&amp;link=&amp;tabs=-Details\"></script>","variants":{"8780570001":{"sku":"8780570001","vendor_sku":"W4GABI314","upc":"883741753301","size":"XS","color":"Black","retail_price":"75.00","sale_price":"75.00"},"8780570002":{"sku":"8780570002","vendor_sku":"W4GABI314","upc":"883741753318","size":"S","color":"Black","retail_price":"75.00","sale_price":"75.00"},"8780570003":{"sku":"8780570003","vendor_sku":"W4GABI314","upc":"883741753325","size":"M","color":"Black","retail_price":"75.00","sale_price":"75.00"},"8780570004":{"sku":"8780570004","vendor_sku":"W4GABI314","upc":"883741753332","size":"L","color":"Black","retail_price":"75.00","sale_price":"75.00"},"8780570005":{"sku":"8780570005","vendor_sku":"W4GABI314","upc":"883741753349","size":"XL","color":"Black","retail_price":"75.00","sale_price":"75.00"}},"categories":["womens","womens-pants","womens-yoga-pants"]}
