{"brand":"Rei","sku":"879776","brand_name":"Rei","product_name":"REI Sahara Hat - Women's","long_description":"Your best friend when the sun is shining relentlessly, this hat's broad brim provides extended coverage and shade.","short_description":"Your best friend when the sun is shining relentlessly, this hat's broad brim provides extended coverage and shade.","category":"Women's Clothing","subcategory":"Women's Clothing Accessories","product_group":"Women's Hats","thumb_url":"http://i1.avlws.com/115/s553095.png","image_url":"http://i1.avlws.com/115/l553095.png","buy_link":"http://www.avantlink.com/click.php?p=81603&pw=55475&pt=3&pri=553095&tt=df","retail_price":"34.50","sale_price":"34.50","product_page_view_tracking":"<img src=\"http://www.avantlink.com/dfpv.php?p=81603&amp;pri=553095\" width=\"0\" height=\"0\" style=\"border: none !important; margin: 0px !important;\" alt=\"\" />","medium_image_url":"http://i1.avlws.com/115/m553095.png","product_content_widget":"<script type=\"text/javascript\" src=\"http://www.avantlink.com/apcw.php?mode=5&amp;pw=55475&amp;df=115&amp;sku=879776&amp;link=&amp;tabs=-Details\"></script>","variants":{"8797760001":{"sku":"8797760001","vendor_sku":"P2C02377B29008","upc":"810990022629","size":"S/M","color":"Wombat","retail_price":"34.50","sale_price":"34.50"},"8797760002":{"sku":"8797760002","vendor_sku":"P2C02377B29010","upc":"810990022636","size":"L/XL","color":"Wombat","retail_price":"34.50","sale_price":"34.50"},"8797760003":{"sku":"8797760003","vendor_sku":"P2C02377B10608","upc":"810990022643","size":"S/M","color":"White","retail_price":"34.50","sale_price":"34.50"},"8797760004":{"sku":"8797760004","vendor_sku":"P2C02377B10610","upc":"810990022650","size":"L/XL","color":"White","retail_price":"34.50","sale_price":"34.50"}},"categories":["womens","womens-clothing-accessories","womens-hats"]}
