{"brand":"The North Face","sku":"881848","brand_name":"The North Face","product_name":"The North Face Ultra 109 GTX Trail-Running Shoes - Women's","long_description":"Blurring the line between hiking and running, these light shoes deliver Gore-Tex protection, stability and traction for women who want to move fast on trails.","short_description":"Blurring the line between hiking and running, these light shoes deliver Gore-Tex protection, stability and traction for women who want to move fast on trails.","category":"Footwear","subcategory":"Women's Footwear","product_group":"Women's Shoes","thumb_url":"http://i1.avlws.com/115/s555655.png","image_url":"http://i1.avlws.com/115/l555655.png","buy_link":"http://www.avantlink.com/click.php?p=81603&pw=55475&pt=3&pri=555655&tt=df","retail_price":"120.00","sale_price":"120.00","product_page_view_tracking":"<img src=\"http://www.avantlink.com/dfpv.php?p=81603&amp;pri=555655\" width=\"0\" height=\"0\" style=\"border: none !important; margin: 0px !important;\" alt=\"\" />","medium_image_url":"http://i1.avlws.com/115/m555655.png","product_content_widget":"<script type=\"text/javascript\" src=\"http://www.avantlink.com/apcw.php?mode=5&amp;pw=55475&amp;df=115&amp;sku=881848&amp;link=&amp;tabs=-Details\"></script>","variants":{"8818480001":{"sku":"8818480001","vendor_sku":"CCP5AQR","upc":"700051679315","size":"6","color":"Steeple Grey/Balsam Blue","retail_price":"120.00","sale_price":"120.00"},"8818480002":{"sku":"8818480002","vendor_sku":"CCP5AQR","upc":"700051679322","size":"6.5","color":"Steeple Grey/Balsam Blue","retail_price":"120.00","sale_price":"120.00"},"8818480003":{"sku":"8818480003","vendor_sku":"CCP5AQR","upc":"700051679339","size":"7","color":"Steeple Grey/Balsam Blue","retail_price":"120.00","sale_price":"120.00"},"8818480004":{"sku":"8818480004","vendor_sku":"CCP5AQR","upc":"700051679278","size":"7.5","color":"Steeple Grey/Balsam Blue","retail_price":"120.00","sale_price":"120.00"},"8818480005":{"sku":"8818480005","vendor_sku":"CCP5AQR","upc":"700051679186","size":"8","color":"Steeple Grey/Balsam Blue","retail_price":"120.00","sale_price":"120.00"},"8818480006":{"sku":"8818480006","vendor_sku":"CCP5AQR","upc":"700051679193","size":"8.5","color":"Steeple Grey/Balsam Blue","retail_price":"120.00","sale_price":"120.00"},"8818480007":{"sku":"8818480007","vendor_sku":"CCP5AQR","upc":"700051679230","size":"9","color":"Steeple Grey/Balsam Blue","retail_price":"120.00","sale_price":"120.00"},"8818480008":{"sku":"8818480008","vendor_sku":"CCP5AQR","upc":"700051679247","size":"9.5","color":"Steeple Grey/Balsam Blue","retail_price":"120.00","sale_price":"120.00"},"8818480009":{"sku":"8818480009","vendor_sku":"CCP5AQR","upc":"700051679285","size":"10","color":"Steeple Grey/Balsam Blue","retail_price":"120.00","sale_price":"120.00"},"8818480010":{"sku":"8818480010","vendor_sku":"CCP5AQR","upc":"700051679292","size":"10.5","color":"Steeple Grey/Balsam Blue","retail_price":"120.00","sale_price":"120.00"},"8818480011":{"sku":"8818480011","vendor_sku":"CCP5AQR","upc":"700051679308","size":"11","color":"Steeple Grey/Balsam Blue","retail_price":"120.00","sale_price":"120.00"}},"categories":["footwear","womens-footwear","womens-shoes"]}
