{"brand":"Swix","sku":"884874","brand_name":"Swix","product_name":"Swix HF7BW High-Fluoro Glide Wax - 18 to 28 Degrees F - 40g","long_description":"Ideal for normal winter conditions below freezing, this easy-application wax with lubricant excels on alpine slopes, cross-country trails and old or artificial snow conditions from 18 to 28F.","short_description":"Ideal for normal winter conditions below freezing, this easy-application wax with lubricant excels on alpine slopes, cross-country trails and old or artificial snow conditions from 18 to 28F.","category":"Skiing","subcategory":"Ski Tuning And Tools","product_group":"Ski Wax","thumb_url":"http://i1.avlws.com/115/s529771.png","image_url":"http://i1.avlws.com/115/l529771.png","buy_link":"http://www.avantlink.com/click.php?p=81603&pw=55475&pt=3&pri=529771&tt=df","retail_price":"99.00","sale_price":"99.00","product_page_view_tracking":"<img src=\"http://www.avantlink.com/dfpv.php?p=81603&amp;pri=529771\" width=\"0\" height=\"0\" style=\"border: none !important; margin: 0px !important;\" alt=\"\" />","medium_image_url":"http://i1.avlws.com/115/m529771.png","product_content_widget":"<script type=\"text/javascript\" src=\"http://www.avantlink.com/apcw.php?mode=5&amp;pw=55475&amp;df=115&amp;sku=884874&amp;link=&amp;tabs=-Details\"></script>","variants":{"8848740001":{"sku":"8848740001","vendor_sku":"HF7BWX-4","size":"40 GRAMS","retail_price":"99.00","sale_price":"99.00"}},"categories":["snow","ski-tuning-and-tools","ski-wax"]}
