{"brand":"Gregory","sku":"887729","brand_name":"Gregory","product_name":"Gregory Tempo Handheld Water Bottle - 2014 Closeout","long_description":"This handheld water bottle is the ideal grab-and-go hydrator for your daily run. Its design reduces grip fatigue while simultaneously providing space for small items like car keys, ID or energy gels.","short_description":"This handheld water bottle is the ideal grab-and-go hydrator for your daily run. Its design reduces grip fatigue while simultaneously providing space for small items like car keys, ID or energy gels.","category":"Fitness","subcategory":"Running","product_group":"Water Bottles And Gel Flasks","thumb_url":"http://i1.avlws.com/115/s555127.png","image_url":"http://i1.avlws.com/115/l555127.png","buy_link":"http://www.avantlink.com/click.php?p=81603&pw=55475&pt=3&pri=555127&tt=df","retail_price":"17.73","sale_price":"17.73","product_page_view_tracking":"<img src=\"http://www.avantlink.com/dfpv.php?p=81603&amp;pri=555127\" width=\"0\" height=\"0\" style=\"border: none !important; margin: 0px !important;\" alt=\"\" />","medium_image_url":"http://i1.avlws.com/115/m555127.png","product_content_widget":"<script type=\"text/javascript\" src=\"http://www.avantlink.com/apcw.php?mode=5&amp;pw=55475&amp;df=115&amp;sku=887729&amp;link=&amp;tabs=-Details\"></script>","variants":{"8877290001":{"sku":"8877290001","vendor_sku":"GM59914","upc":"844930070517","size":"One Size","color":"Lightning Gray","retail_price":"17.73","sale_price":"17.73"}},"categories":["fitness","running","water-bottles-and-gel-flasks"]}
