{"brand":"Timberland","sku":"888252","brand_name":"Timberland","product_name":"Timberland Savin Hill Tall Boots - Women's","long_description":"These riding-inspired boots feature handcrafted details and shiny buckles to make them a focal point of your outfit. Their classic style is perfect for wearing with your cool-weather ensembles.","short_description":"These riding-inspired boots feature handcrafted details and shiny buckles to make them a focal point of your outfit. Their classic style is perfect for wearing with your cool-weather ensembles.","category":"Footwear","subcategory":"Women's Footwear","product_group":"Women's Boots","thumb_url":"http://i1.avlws.com/115/s550551.png","image_url":"http://i1.avlws.com/115/l550551.png","buy_link":"http://www.avantlink.com/click.php?p=81603&pw=55475&pt=3&pri=550551&tt=df","retail_price":"240.00","sale_price":"240.00","product_page_view_tracking":"<img src=\"http://www.avantlink.com/dfpv.php?p=81603&amp;pri=550551\" width=\"0\" height=\"0\" style=\"border: none !important; margin: 0px !important;\" alt=\"\" />","medium_image_url":"http://i1.avlws.com/115/m550551.png","product_content_widget":"<script type=\"text/javascript\" src=\"http://www.avantlink.com/apcw.php?mode=5&amp;pw=55475&amp;df=115&amp;sku=888252&amp;link=&amp;tabs=-Details\"></script>","variants":{"8882520002":{"sku":"8882520002","vendor_sku":"TB08549R001","upc":"887235744523","size":"6.5","color":"Black Smooth","retail_price":"240.00","sale_price":"240.00"},"8882520003":{"sku":"8882520003","vendor_sku":"TB08549R001","upc":"887235744530","size":"7","color":"Black Smooth","retail_price":"240.00","sale_price":"240.00"},"8882520005":{"sku":"8882520005","vendor_sku":"TB08549R001","upc":"887235744554","size":"8","color":"Black Smooth","retail_price":"240.00","sale_price":"240.00"},"8882520006":{"sku":"8882520006","vendor_sku":"TB08549R001","upc":"887235744561","size":"8.5","color":"Black Smooth","retail_price":"240.00","sale_price":"240.00"}},"categories":["footwear","womens-footwear","womens-boots"]}
