{"bought":{"862798":{"title":" prAna Horton Shorts - Men's - 2013 Closeout","sale_price":"48.73","url":"/mens/mens-shorts/mens-casual-shorts/862798.html"},"845015":{"title":" The North Face Apex Washoe Shorts - Men's","sale_price":"65.00","url":"/mens/mens-shorts/mens-water-shorts/845015.html"},"873521":{"title":" The North Face Paramount Traverse Pants - Men's - 2013 Closeout","sale_price":"48.73","url":"/mens/mens-pants/mens-hiking-pants/873521.html"},"873519":{"title":" The North Face Buckland Pants - Men's - 2013 Closeout","sale_price":"59.73","url":"/mens/mens-pants/mens-casual-pants/873519.html"}},"viewed":{"864997":{"title":" Merrell Amani Ditto Sandals - Girls' - 2013 Closeout","sale_price":"27.73","url":"/footwear/kids-footwear/kids-sandals/864997.html"},"813508":{"title":" SOL Rescue Howler Whistle - Package of 2","sale_price":"8.95","url":"/camping-hiking/health-and-safety/emergency-and-survival/813508.html"},"858197":{"title":" Baffin Kona Winter Boots - Women's - 2012 Closeout","sale_price":"118.73","url":"/footwear/womens-footwear/womens-boots/858197.html"},"862562":{"title":" Lole Fly Tank Top - Women's - 2013 Closeout","sale_price":"36.73","url":"/womens/womens-shirts/womens-tanks/862562.html"}},"together":{"873963":{"title":" Arbor Burnside Stretch Twill Pants - Men's 32\" Inseam - 2013 Closeout","sale_price":"51.73","url":"/mens/mens-pants/mens-casual-pants/873963.html"}}}
