{"bought":{"810009":{"title":"Ergon GP1 BioKork Handlebar Grips","sale_price":"39.95","url":"/cycling/bike-components/handlebars-and-accessories/810009.html"},"864756":{"title":"CygoLite TridenX 1300 OSP Front Bike Light","sale_price":"249.95","url":"/cycling/bike-accessories/bike-lights/864756.html"},"861473":{"title":"Marin San Anselmo DS2 Step-Through Women's Bike - 2014","sale_price":"549.00","url":"/cycling/bikes/hybrid-bikes/861473.html"},"819881":{"title":"Pearl Izumi Elite Barrier Shoe Covers","sale_price":"70.00","url":"/cycling/cycling-clothing/cycling-clothing-accessories/819881.html"}},"viewed":{"867251":{"title":"White Sierra Swamp Shirt - Men's - Special Buy","sale_price":"30.73","url":"/mens/mens-shirts/mens-hiking-travel-shirts/867251.html"},"849560":{"title":"Trails of Crater Lake National Park and Oregon Caves National Monument","sale_price":"14.95","url":"/books/guidebooks/camping-and-hiking-guidebooks/849560.html"},"866801":{"title":"Pink Lotus Gathered Momentum Capri Pants - Women's","sale_price":"42.00","url":"/womens/womens-pants/womens-yoga-pants/866801.html"},"859377":{"title":"Rossignol Temptation 82 Skis with Bindings - Women's - 2013/2014","sale_price":"699.95","url":"/snow/skis/downhill-skis/859377.html"}},"together":{"832957":{"title":"Continental X-King Bike Tire - 26 x 2.2 / 26 x 2.4","sale_price":"35.00","url":"/cycling/bike-components/bike-tires-tubes-and-wheels/832957.html"}}}
