{"bought":{"867035":{"title":" TYR Phoenix Splice Jammer Swimsuit - Men's","sale_price":"50.00","url":"/mens/mens-swimwear/mens-swimsuits/867035.html"},"863735":{"title":" Patagonia Nine Trails Knickers - Men's","sale_price":"75.00","url":"/mens/mens-pants/mens-running-pants-and-tights/863735.html"},"874760":{"title":" Mountain Khakis Teton Flannel Shirt - Men's - 2013 Closeout","sale_price":"54.73","url":"/mens/mens-shirts/mens-casual-shirts/874760.html"},"868606":{"title":" O'Neill Skins Crew Long-Sleeve Rashguard - Men's","sale_price":"41.95","url":"/mens/mens-shirts/mens-rashguards/868606.html"}},"viewed":{"782057":{"title":" Osprey Map Wrap Map Case","sale_price":"19.50","url":"/books-and-maps/maps/map-accessories/782057.html"},"844697":{"title":" Sunday Afternoons Kauai Hat - Women's","sale_price":"30.00","url":"/womens/womens-clothing-accessories/womens-hats/844697.html"},"753748":{"title":" Novara Storage Hooks - Pair","sale_price":"3.00","url":"/car-racks/garage-storage/bike-storage-racks/753748.html"},"866475":{"title":" Raleigh Venture 3.0 Step-Through Women's Bike - 2014","sale_price":"399.00","url":"/cycling/bikes/hybrid-bikes/866475.html"}},"together":{"852217":{"title":" Merrell Sharp Peak Insulated Jacket - Men's - 2012 Closeout","sale_price":"159.73","url":"/mens/mens-jackets/mens-rain-jackets/852217.html"}}}
