{"bought":{"848242":{"title":" La Sportiva Wildcat 2.0 GTX Trail-Running Shoes - Men's","sale_price":"155.00","url":"/footwear/mens-footwear/mens-shoes/848242.html"},"849029":{"title":" Salewa Rapace Gore-Tex Mountaineering Boots - Men's","sale_price":"279.00","url":"/footwear/mens-footwear/mens-boots/849029.html"},"866695":{"title":" ICEBUG Anima BUGrip Road-Running Shoes - Men's - 2012 Closeout","sale_price":"117.73","url":"/footwear/mens-footwear/mens-shoes/866695.html"},"864947":{"title":" Merrell Mix Master Maze Sport Shoes- Men's - 2013 Closeout","sale_price":"64.73","url":"/footwear/mens-footwear/mens-shoes/864947.html"}},"viewed":{"867297":{"title":" CamelBak Rim Runner 22 Hydration Pack - 100 fl. oz.","sale_price":"100.00","url":"/camping-hiking/backpacks/day-packs/867297.html"},"874944":{"title":" Primal Wear Parts Bike Jersey - Men's - 2011 Overstock","sale_price":"46.73","url":"/cycling/cycling-clothing/cycling-jerseys/874944.html"},"624234":{"title":" CytoSport Cytomax Sports Performance Drink Mix - 27 Serving","sale_price":"20.00","url":"/camping-hiking/camp-kitchen/food/624234.html"},"873073":{"title":" Ergon GP5 Bike Grips","sale_price":"69.95","url":"/cycling/bike-components/handlebars-and-accessories/873073.html"}},"together":{"866099":{"title":" adidas Terrex Fast X Mid GTX Hiking Boots - Men's","sale_price":"185.00","url":"/footwear/mens-footwear/mens-boots/866099.html"}}}
