{"bought":{"858291":{"title":"Amphipod Hydraform Handheld Ergo-Lite Water Bottle - 10.5 fl. oz.","sale_price":"15.93","url":"/fitness/running/water-bottles-and-gel-flasks/858291.html"},"867685":{"title":"Thule Chariot Chinook 2 Stroller","sale_price":"1299.95","url":"/fitness/running/strollers/867685.html"},"857728":{"title":"Fitbit Flex Wristband Accessory Pack","sale_price":"29.95","url":"/fitness/running/fitness-electronics/857728.html"},"867690":{"title":"Thule Chariot Cougar 1 Stroller with Stroller Kit","sale_price":"674.95","url":"/fitness/running/strollers/867690.html"}},"viewed":{"885117":{"title":"Merrell Elsand Half-Zip Pullover - Men's - 2014 Closeout","sale_price":"44.73","url":"/mens/mens-sweaters-and-hoodies/mens-pullover-sweaters/885117.html"},"721671":{"title":"Outdoor Research Sun Runner Cap","sale_price":"35.00","url":"/mens/mens-clothing-accessories/mens-hats/721671.html"},"843748":{"title":"FalconGuides Rock Climbing Minnesota and Wisconsin - 2nd Edition","sale_price":"30.00","url":"/books/guidebooks/climbing-guidebooks/843748.html"},"777606":{"title":"REI XR 8 x 32 Waterproof Binoculars","sale_price":"129.00","url":"/camping-hiking/gadgets/binoculars-and-optics/777606.html"}},"together":{"794021":{"title":"Hugger Mugger Foam Yoga Block","sale_price":"14.95","url":"/fitness/yoga/yoga-props/794021.html"}}}
