{"bought":{"777835":{"title":"Swix Nordic Travelvise Ski Vise Set","sale_price":"124.95","url":"/snow/ski-tuning-and-tools/ski-tuning-equipment/777835.html"},"875897":{"title":"Roxy Torah Bright XC2 BTX Snowboard - Women's - 2014/2015","sale_price":"431.93","url":"/snow/snowboards/allmountain-snowboards/875897.html"},"859591":{"title":"Ortovox ABS Activation Cylinder - Full","sale_price":"147.93","url":"/snow/ski-packs-and-bags/ski-packs/859591.html"},"860849":{"title":"Spark R&D Tesla System Magneto Baseplate Kit","sale_price":"199.93","url":"/snow/snowboard-bindings/snowboard-binding-accessories/860849.html"}},"viewed":{"850679":{"title":"Princeton Tec Vizz Headlamp","sale_price":"49.95","url":"/camping-hiking/camp-lighting/headlamps/850679.html"},"746012":{"title":"Mountaineers Books Olympic Mountains: A Climbing Guide - 4th Edition","sale_price":"19.95","url":"/books/guidebooks/climbing-guidebooks/746012.html"},"852184":{"title":"Racktime Top-It Front Bike Rack","sale_price":"54.95","url":"/cycling/bike-accessories/panniers-and-onbike-packs/852184.html"},"882146":{"title":"GoPro HERO4 Black Camera - Surf/SUP/Kayak Edition","sale_price":"499.95","url":"/electronics/helmet-cameras/helmet-cams/882146.html"}},"together":{"859665":{"title":"Icelantic Skis Shaman Skis - Men's - 2013/2014","sale_price":"373.93","url":"/snow/skis/downhill-skis/859665.html"}}}
