{"bought":{"872394":{"title":"Mountain Hardwear Minalist Snow Shell Pants - Men's","sale_price":"242.93","url":"/mens/mens-pants/mens-snow-pants/872394.html"},"876923":{"title":"Westcomb Tango Hoodie Jacket - Men's","sale_price":"124.83","url":"/mens/mens-jackets/mens-insulated-jackets/876923.html"},"871355":{"title":"The North Face Torpedo Jacket - Men's","sale_price":"68.93","url":"/mens/mens-jackets/mens-running-jackets/871355.html"},"879342":{"title":"Mountain Hardwear Logo Tee - Men's - 2014 Closeout","sale_price":"15.73","url":"/mens/mens-shirts/mens-casual-shirts/879342.html"}},"viewed":{"883647":{"title":"Earth Biscayne Stand Up Paddleboard - 12' 6\" x 28\"","sale_price":"2199.95","url":"/paddling/paddle-boarding/paddle-boards/883647.html"},"872435":{"title":"Columbia Shimmerlicious Insulated Jacket - Women's","sale_price":"200.00","url":"/womens/womens-jackets/womens-insulated-jackets/872435.html"},"874817":{"title":"DAKINE Fall Line Double Ski Bag - Women's","sale_price":"90.93","url":"/snow/ski-packs-and-bags/ski-bags/874817.html"},"722563":{"title":"Wilderness Press Afoot and Afield San Francisco Bay Area: A Comprehensive Hiking Guide","sale_price":"16.95","url":"/books/guidebooks/camping-and-hiking-guidebooks/722563.html"}},"together":{"872581":{"title":"Salomon Endurance Tights - Men's","sale_price":"58.93","url":"/mens/mens-pants/mens-running-pants-and-tights/872581.html"}}}
