{"bought":{"874229":{"title":"Burton Splitboard Daypack","sale_price":"74.93","url":"/snow/ski-packs-and-bags/ski-packs/874229.html"},"876124":{"title":"Volkl RTM Jr Skis with Bindings - Kids' - 2014/2015","sale_price":"249.00","url":"/snow/skis/downhill-skis/876124.html"},"842596":{"title":"Swix UR8 Red Bio Racing Wax","sale_price":"25.95","url":"/snow/ski-tuning-and-tools/ski-wax/842596.html"},"859454":{"title":"Rossignol Axium JR 70 Downhill Ski Bindings - Juniors","sale_price":"95.93","url":"/snow/ski-bindings/downhill-ski-bindings/859454.html"}},"viewed":{"709707":{"title":"Mountaineers Books Washington Ice: A Climbing Guide","sale_price":"21.95","url":"/books/guidebooks/climbing-guidebooks/709707.html"},"884847":{"title":"Slackline Industries Baseline Slackline with TreePro and Instructional DVD - 50 ft.","sale_price":"75.00","url":"/climbing/webbing-and-cords/slacklines/884847.html"},"881939":{"title":"Mountain Khakis Anytime Cargo Shorts - 9.5\" Inseam - Women's - 2014 Closeout","sale_price":"42.73","url":"/womens/womens-shorts/womens-casual-shorts/881939.html"},"710406":{"title":"Topeak Aero Expanding Wedge - Medium","sale_price":"34.95","url":"/cycling/bike-accessories/panniers-and-onbike-packs/710406.html"}},"together":{"875836":{"title":"GNU Beast DC3 BTX Snowboard - 2014/2015","sale_price":"431.93","url":"/snow/snowboards/freeride-snowboards/875836.html"}}}
